[
  {
    "id": 638,
    "name": "ACPowerDelivered",
    "displayName": "AC Power",
    "description": "AC Power produced by plant, delivered to grid",
    "dataFormat": "{0:#,##0}"
  },
  {
    "id": 628,
    "name": "ActiveStateFlag",
    "displayName": "Active State Flag",
    "description": "Indictor describing if the turbine or generator is active/online",
    "dataFormat": ""
  },
  {
    "id": 49,
    "name": "ActualGrossMw",
    "displayName": "Gross MW",
    "description": "Total number of MW produced by generating unit",
    "dataFormat": "{0:#,##0.0}"
  },
  {
    "id": 8,
    "name": "ActualHr",
    "displayName": "Heat Rate (MMBTU/MWh)",
    "description": "Rate at which fuel is burned to produce power.  Serves as measurement of plant efficiency.",
    "dataFormat": "{0:#,##0.0}"
  },
  {
    "id": 35,
    "name": "actualStartCount",
    "displayName": "#Starts",
    "description": "Number of Unit Start (Breaker Closed Events)",
    "dataFormat": "{0:#,##0.0}"
  },
  {
    "id": 886,
    "name": "ActualStartsCalc",
    "displayName": "Actual Starts Calc",
    "description": "",
    "dataFormat": "{0:#,##0.0}"
  },
  {
    "id": 870,
    "name": "ADSSubmission",
    "displayName": "ADS Submission",
    "description": "",
    "dataFormat": "{0:#,##0.00}"
  },
  {
    "id": 534,
    "name": "AGC Dynamic Schedule",
    "displayName": "AGC Dynamic Schedule",
    "description": "AGC Dynamic Schedule",
    "dataFormat": "{0:#,##0.0}"
  },
  {
    "id": 871,
    "name": "ALFSForecast",
    "displayName": "ALFSForecast",
    "description": "ALFSForecast",
    "dataFormat": "{0:#,##0.0}"
  },
  {
    "id": 864,
    "name": "AmbientTemp",
    "displayName": "Ambient Temp",
    "description": "Temperature which surrounds an object",
    "dataFormat": "{0:#,##0}"
  },
  {
    "id": 2012,
    "name": "Annual Path 26 Constraints",
    "displayName": "Annual Path 26 Constraints",
    "description": "Temp. Metric, Can be deleted after demo 4/4",
    "dataFormat": ""
  },
  {
    "id": 184,
    "name": "attemptedStarts",
    "displayName": "Attempted Starts",
    "description": "Number of attempted unit starts.",
    "dataFormat": "{0:#,##0}"
  },
  {
    "id": 869,
    "name": "AutomatedETR",
    "displayName": "Automated ETR",
    "description": "",
    "dataFormat": "{0:#,##0.0}"
  },
  {
    "id": 868,
    "name": "AutomatedNatureOfWork",
    "displayName": "Automated Nature Of Work",
    "description": "",
    "dataFormat": "{0:#,##0.0}"
  },
  {
    "id": 866,
    "name": "AutomatedRampRate",
    "displayName": "Automated Ramp Rate",
    "description": "",
    "dataFormat": "{0:#,##0.0}"
  },
  {
    "id": 867,
    "name": "AutomatedUpperRegLimit",
    "displayName": "Automated Upper Reg Limit",
    "description": "",
    "dataFormat": "{0:#,##0.0}"
  },
  {
    "id": 249,
    "name": "Aux Power MWh",
    "displayName": "Aux Power",
    "description": "Amount of power required to operate the plant/station",
    "dataFormat": "{0:#,##0.0}"
  },
  {
    "id": 38,
    "name": "avail_AvailabileMW",
    "displayName": "Available MW",
    "description": "A unit's capacity minus any derates or outages",
    "dataFormat": "{0:#,##0.0}"
  },
  {
    "id": 36,
    "name": "avail_BoilerPlateMW",
    "displayName": "Capacity (Nameplate)",
    "description": "MW Amount a unit can generate (not adjusted for weather)",
    "dataFormat": "{0:#,##0.0}"
  },
  {
    "id": 76,
    "name": "availabilityPct",
    "displayName": "Availability %",
    "description": "Percent of unit's capacity - any derates or outages (Available MW/Unit Capacity)",
    "dataFormat": "{0:#,##0.0}"
  },
  {
    "id": 442,
    "name": "AvailHours",
    "displayName": "AH",
    "description": "Number of Hours a plant is available",
    "dataFormat": "{0:#,##0.0}"
  },
  {
    "id": 468,
    "name": "AvgCostAtActMWh",
    "displayName": "Average Cost @Act MWh",
    "description": "Using Unit cost curve, averege cost of generating at Unit Capacity (average cost for each MW from 0 ",
    "dataFormat": "{0:#,##0.00}"
  },
  {
    "id": 467,
    "name": "AvgCostAtFullLoad",
    "displayName": "Average Cost @ Full Load",
    "description": "Using Unit cost curve, averege cost of generating at Unit Capacity (average cost for each MW from 0 ",
    "dataFormat": "{0:#,##0.00}"
  },
  {
    "id": 713,
    "name": "AvgCostAtSchedMWh ",
    "displayName": "Average Cost @Sched MWh",
    "description": "",
    "dataFormat": "{0:#,##0.00}"
  },
  {
    "id": 164,
    "name": "AVR",
    "displayName": "AVR Status",
    "description": "Status of Automatic Voltage Regulation equipment (usually Auto or Manual).  Compliance related issue",
    "dataFormat": "{0:#,##0}"
  },
  {
    "id": 113,
    "name": "BankTurbinesOnLine",
    "displayName": "Turbines Online",
    "description": "Number of turbines online and currently producing electricity",
    "dataFormat": "{0:#,##0}"
  },
  {
    "id": 118,
    "name": "BankTurbinesUnAvailable",
    "displayName": "Bank Turbines UnAvailable",
    "description": "",
    "dataFormat": "{0:#,##0.00}"
  },
  {
    "id": 469,
    "name": "BarometricPressure",
    "displayName": "Barometric Pressure",
    "description": "BP measured at unit",
    "dataFormat": "{0:#,##0.0}"
  },
  {
    "id": 2004,
    "name": "Base Forecast Adj",
    "displayName": "Base Forecast Adj",
    "description": "Temp. Metric, Can be deleted after demo 4/4",
    "dataFormat": ""
  },
  {
    "id": 642,
    "name": "BudgetedGenerationAccumulated",
    "displayName": "Budgeted Generation To Date",
    "description": "The amount of generation budget alotted to a time period based on accumlator from Scada/PI ",
    "dataFormat": "{0:#,##0.0}"
  },
  {
    "id": 512,
    "name": "BypassFlow",
    "displayName": "BypassFlow (cfs)",
    "description": "Bypass Flow (cfs)",
    "dataFormat": "{0:0##,##0.00}"
  },
  {
    "id": 2008,
    "name": "CAM",
    "displayName": "CAM",
    "description": "Temp. Metric, Can be deleted after demo 4/4",
    "dataFormat": ""
  },
  {
    "id": 79,
    "name": "capacityFactor",
    "displayName": "Capacity Factor",
    "description": "Percent of unit capability used for generation =MW/Capability*100%",
    "dataFormat": "{0:#,##0.00}"
  },
  {
    "id": 633,
    "name": "capacityFactorAccumated",
    "displayName": "Capacity Factor Accumated",
    "description": "Percent of unit capability used for generation =MW/Capability*100% based on accumlator from Scada/PI",
    "dataFormat": "{0:#,##0.00}"
  },
  {
    "id": 2005,
    "name": "CEC Forecast",
    "displayName": "CEC Forecast",
    "description": "Temp. Metric, Can be deleted after demo 4/4",
    "dataFormat": ""
  },
  {
    "id": 770,
    "name": "CertfiedForReg",
    "displayName": "Certfied For Reg",
    "description": "",
    "dataFormat": "{0:#,##0.0}"
  },
  {
    "id": 771,
    "name": "CertfiedForSpin",
    "displayName": "Certfied For Spin",
    "description": "",
    "dataFormat": "{0:#,##0.0}"
  },
  {
    "id": 772,
    "name": "CertifiedForAsDamNonSpin",
    "displayName": "Certified For As Dam Non Spin",
    "description": "",
    "dataFormat": "{0:#,##0.0}"
  },
  {
    "id": 773,
    "name": "CertifiedForAsRtmNonSpin",
    "displayName": "Certified For As Rtm Non Spin",
    "description": "",
    "dataFormat": "{0:#,##0.0}"
  },
  {
    "id": 438,
    "name": "commercialAvailability",
    "displayName": "Commercial Availability",
    "description": "Measurement of Availability (when unit is In The Money)",
    "dataFormat": "{0:#,##0.00}"
  },
  {
    "id": 639,
    "name": "CommStatus",
    "displayName": "Communication Status",
    "description": "The current status of communication to the unit. This can give a heartbeat to the activity of the un",
    "dataFormat": "{0:#,##0.0}"
  },
  {
    "id": 641,
    "name": "ComponentUnavailabilityHours",
    "displayName": "Component Unavailability Hours",
    "description": "The hours in the Period when minimum POA irradiance conditions persisting for periods greater than o",
    "dataFormat": "{0:#,##0.0}"
  },
  {
    "id": 774,
    "name": "CoolingTime",
    "displayName": "Cooling Time",
    "description": "",
    "dataFormat": "{0:#,##0.0}"
  },
  {
    "id": 622,
    "name": "CorrelationIndex",
    "displayName": "Correlation Index",
    "description": "Describes the efficiency when the unit is running vs. the overall production efficiency.  Operating ",
    "dataFormat": "{0:#,##0.00}"
  },
  {
    "id": 775,
    "name": "CostAtMinLoad",
    "displayName": "Cost At Min Load",
    "description": "",
    "dataFormat": "{0:#,##0.0}"
  },
  {
    "id": 602,
    "name": "CTH",
    "displayName": "Contact Turbine-Hours (CTH)",
    "description": "Total number of hours that turbines are generating (number of hours generating * number of turbines)",
    "dataFormat": "{0:##0.0}"
  },
  {
    "id": 860,
    "name": "Curtailed To",
    "displayName": "Curtailed To",
    "description": "The MW setpoint a Location has been restricted to operate during a specific time period (A 100 MW Wi",
    "dataFormat": ""
  },
  {
    "id": 634,
    "name": "CurtailmentStatus",
    "displayName": "Curtailment Status",
    "description": "The curailment status code of a location sourced from Scada/PI",
    "dataFormat": "{0:#,##0.00}"
  },
  {
    "id": 537,
    "name": "CutInWindSpeed",
    "displayName": "CutInWindSpeed(ms)",
    "description": "Cut-in Wind Speed - min wind speed",
    "dataFormat": "{0:##0}"
  },
  {
    "id": 538,
    "name": "CutOutWindSpeed",
    "displayName": "CutOutWindSpeed(ms)",
    "description": "Cut-out Wind Speed - max wind Speed",
    "dataFormat": "{0:##0}"
  },
  {
    "id": 2016,
    "name": "DA Revenue",
    "displayName": "DA Revenue",
    "description": "DA Revenue",
    "dataFormat": "{0:#,##0.00}"
  },
  {
    "id": 472,
    "name": "DAForecastMAPE",
    "displayName": "DA Forecast MAPE",
    "description": "Mean Average Percent Error between DA Forecast and actual generation (Act - DA Forecast)/Act",
    "dataFormat": "{0:#,##0.00}"
  },
  {
    "id": 459,
    "name": "DamElevation",
    "displayName": "Dam Elevation",
    "description": "Height of water on high side of dam.",
    "dataFormat": "{0:#,##0.0}"
  },
  {
    "id": 455,
    "name": "damGate",
    "displayName": "Dam Gate",
    "description": "Percentage that a hydro unit's gate is opened to allow water through a hydro unit to generate power.",
    "dataFormat": "{0:#,##0.0}"
  },
  {
    "id": 456,
    "name": "DamInFlow",
    "displayName": "Dam In Flow",
    "description": "Flow rate on high side of dam.",
    "dataFormat": "{0:#,##0.0}"
  },
  {
    "id": 457,
    "name": "DamOutFlow",
    "displayName": "Dam Out Flow",
    "description": "Flow Rate on low side of dam",
    "dataFormat": "{0:#,##0.0}"
  },
  {
    "id": 458,
    "name": "DamStorage",
    "displayName": "Dam Storage",
    "description": "Potential energy available from dam, based on pond levels",
    "dataFormat": "{0:#,##0.0}"
  },
  {
    "id": 101,
    "name": "Day-Ahead energy price",
    "displayName": "DA Price",
    "description": "",
    "dataFormat": "{0:#,##0.00}"
  },
  {
    "id": 471,
    "name": "DayAheadForecast",
    "displayName": "DA Forecast",
    "description": "Snapshot of power forecast taken on a Day Ahead basis, usually used for DA scheduling activity",
    "dataFormat": "{0:#,##0.0}"
  },
  {
    "id": 857,
    "name": "DefaultRAPathSequence",
    "displayName": "Default RA Path Sequence",
    "description": "",
    "dataFormat": "{0:#,##0.0}"
  },
  {
    "id": 80,
    "name": "Deployed Regulation MW",
    "displayName": "Reg Deployed MW",
    "description": "Regulation is an ancillary service where plant can quickly move/change generation output based on a ",
    "dataFormat": "{0:#,##0.0}"
  },
  {
    "id": 81,
    "name": "Deployed Spin MW",
    "displayName": "Spin Deployed MW",
    "description": "Spinning Reserve is an ancillary service where plant can move/change generation in short timeframe o",
    "dataFormat": "{0:#,##0.0}"
  },
  {
    "id": 449,
    "name": "DeviationFromSchedule",
    "displayName": "Deviation From Schedule",
    "description": "Difference between scheduled MW and what is delivered to grid",
    "dataFormat": "{0:#,##0.0}"
  },
  {
    "id": 450,
    "name": "DeviationFromSetPoint",
    "displayName": "Deviation From Set Point",
    "description": "Difference between what is requested (setpoint) and what is delivered to the grid",
    "dataFormat": "{0:#,##0.0}"
  },
  {
    "id": 2007,
    "name": "DR",
    "displayName": "DR",
    "description": "Temp. Metric, Can be deleted after demo 4/4",
    "dataFormat": ""
  },
  {
    "id": 489,
    "name": "DryBulbTemp",
    "displayName": "Dry Bulb Temp",
    "description": "The temperature of air freely exposed to the air but shielded from radiation and moisture.",
    "dataFormat": "{0:##0.00}"
  },
  {
    "id": 882,
    "name": "EconomicBasepoint",
    "displayName": "Economic Basepoint",
    "description": "",
    "dataFormat": "{0:#,##0.0}"
  },
  {
    "id": 40,
    "name": "efdh",
    "displayName": "EFDH",
    "description": "Equivalent Forced Derated Hours (All Forced Derated Hours) =( Forced Derated Hours * Size of Reducti",
    "dataFormat": "{0:#,##0.0}"
  },
  {
    "id": 41,
    "name": "efdhrs",
    "displayName": "EFDHRS",
    "description": "Running Total of EFDH, which resets to 0 at the beginning of the month",
    "dataFormat": "{0:#,##0.0}"
  },
  {
    "id": 434,
    "name": "efof",
    "displayName": "EFOF",
    "description": "Equivalent Forced Outage Factor = ((FOH+EFDH)/PH)*100 Event Types: FOH: U1, U2, U3 and SF; EFDH: D1,",
    "dataFormat": "{0:#,##0.00}"
  },
  {
    "id": 77,
    "name": "efor",
    "displayName": "EFOR",
    "description": "Forced Outage Rate, accounting for outages and derates.  =((FOH+EFDH)/(FOH+SH+EFDHRS))*100% Event Ty",
    "dataFormat": "{0:#,##0.00}"
  },
  {
    "id": 435,
    "name": "eford",
    "displayName": "EFOR-D",
    "description": "",
    "dataFormat": "{0:#,##0.00}"
  },
  {
    "id": 436,
    "name": "eforp",
    "displayName": "EFOR-P",
    "description": "",
    "dataFormat": "{0:#,##0.00}"
  },
  {
    "id": 0,
    "name": "Elevation",
    "displayName": "Elevation",
    "description": "Pond level of water on high side of dam",
    "dataFormat": "{0:#,##0}"
  },
  {
    "id": 443,
    "name": "EMDH",
    "displayName": "EMDH",
    "description": "Number of hours (adjusted for size of derate vs plant capacity) where Maintenance derate exists",
    "dataFormat": "{0:#,##0.0}"
  },
  {
    "id": 432,
    "name": "Equivalent AvailabilityEAF",
    "displayName": "EAF",
    "description": "Percentage of time turbine or site is available to generate. EAF=AH-(EUDH+EPDH+ESEDH))/PH*100%",
    "dataFormat": "{0:#,##0.00}"
  },
  {
    "id": 183,
    "name": "equivPlannedDeratedHours",
    "displayName": "EPDH",
    "description": "Number of hours (adjusted for size of derate vs plant capacity) where planned derate exists = ( PDH ",
    "dataFormat": "{0:#,##0.0}"
  },
  {
    "id": 182,
    "name": "equivScheduledExtensionDeratedHours",
    "displayName": "ESCDH",
    "description": "",
    "dataFormat": "{0:#,##0.0}"
  },
  {
    "id": 181,
    "name": "equivUnplannedDeratedHours",
    "displayName": "EUDH",
    "description": "Number of hours (adjusted for size of derate vs plant capacity) where Unplanned or forced derate exi",
    "dataFormat": "{0:#,##0.0}"
  },
  {
    "id": 520,
    "name": "Expected Power",
    "displayName": "RA Requirement",
    "description": "Expected power output of turbine based on design curve and wind speed",
    "dataFormat": "{0:#,##0.0}"
  },
  {
    "id": 463,
    "name": "ExpectedMargin",
    "displayName": "Expected Margin",
    "description": "Expected Revenue from the plant (DA$* Scheduled MW)",
    "dataFormat": "{0:#,##0}"
  },
  {
    "id": 519,
    "name": "ExpectedMwAvailable",
    "displayName": "ExpectedMwAvailable",
    "description": "Expected Mw Available as provided by Plant engineers",
    "dataFormat": "{0:0##,##0.00}"
  },
  {
    "id": 259,
    "name": "FiredHours",
    "displayName": "Operating Hrs",
    "description": "Amount of time that a turbine is running.",
    "dataFormat": "{0:#,##0}"
  },
  {
    "id": 484,
    "name": "Fogger",
    "displayName": "Fogger ",
    "description": "Fogger Status",
    "dataFormat": ""
  },
  {
    "id": 405,
    "name": "foggingInletTemp",
    "displayName": "foggingInletTemp",
    "description": "foggingInletTemp",
    "dataFormat": "{0:0,##0.00}"
  },
  {
    "id": 44,
    "name": "foh",
    "displayName": "FOH",
    "description": "Number of Hours where Forced outage exists (accounts for partial hours)",
    "dataFormat": "{0:#,##0.0}"
  },
  {
    "id": 510,
    "name": "ForebayElevation",
    "displayName": "ForebayElevation (ft)",
    "description": "ForebayElevation (ft)",
    "dataFormat": "{0:0##,##0.00}"
  },
  {
    "id": 287,
    "name": "Forecasted MW",
    "displayName": "HA Forecast",
    "description": "Hour Ahead Forecasted MW",
    "dataFormat": "{0:#,##0.0}"
  },
  {
    "id": 499,
    "name": "ForecastedInflow3Tier",
    "displayName": "3Tier Inflow",
    "description": "ForecastedInflow(3Tier) - Natural",
    "dataFormat": "{0:0,##0.00}"
  },
  {
    "id": 503,
    "name": "ForecastedInflowNOAA",
    "displayName": "NOAA Inflow",
    "description": "ForecastedInflow(NOAA)",
    "dataFormat": "{0:0,##0.00}"
  },
  {
    "id": 502,
    "name": "ForecastedInflowUSGS",
    "displayName": "USGS Inflow",
    "description": "ForecastedInflow(USGS)",
    "dataFormat": "{0:0,##0.00}"
  },
  {
    "id": 508,
    "name": "ForecastedPressureGH",
    "displayName": "ForecastedPressure(GH)",
    "description": "ForecastedPressure(GH)",
    "dataFormat": "{0:0,##0.00}"
  },
  {
    "id": 507,
    "name": "ForecastedTemperatureGH",
    "displayName": "ForecastedTemperature(GH)",
    "description": "Temperature forecasted by Garrad Hassan",
    "dataFormat": "{0:0,##0.00}"
  },
  {
    "id": 506,
    "name": "ForecastedWindDirectionGH",
    "displayName": "ForecastedWindDirection(GH)",
    "description": "Wind direction forecasted by Garrad Hassan",
    "dataFormat": "{0:0,##0.00}"
  },
  {
    "id": 710,
    "name": "ForwardPrice",
    "displayName": "Forward Price",
    "description": "TBD",
    "dataFormat": ""
  },
  {
    "id": 526,
    "name": "Frequency",
    "displayName": "Frequency",
    "description": "Actual Frequency",
    "dataFormat": "{0:##0.000}"
  },
  {
    "id": 524,
    "name": "FrequencyComponent",
    "displayName": "ACE Frequency Component",
    "description": "The frequency component of the RAW ACE calculation",
    "dataFormat": "{0:##0.000}"
  },
  {
    "id": 603,
    "name": "FTH",
    "displayName": "Forced Turbine-Hours (FTH)",
    "description": "Total number of hours that turbines are in a Forced Outage State",
    "dataFormat": "{0:##0.0}"
  },
  {
    "id": 19,
    "name": "FuelBurnMBTU",
    "displayName": "Fuel Burn (MMBTU)",
    "description": "Amount of Fuel burned to produce power",
    "dataFormat": "{0:#,##0.0}"
  },
  {
    "id": 488,
    "name": "FuelFlowRatePPH",
    "displayName": "Fuel Flow Rate (PPH)",
    "description": "The Rate of Fuel Flow in Pounds Per Hour",
    "dataFormat": "{0:##0.00}"
  },
  {
    "id": 486,
    "name": "FuelFlowSCFM",
    "displayName": "FuelFlowSCFM",
    "description": "Fuel Flow rate in SCFM",
    "dataFormat": "{0:#,##0.00}"
  },
  {
    "id": 46,
    "name": "fuelPrice",
    "displayName": "Fuel Price",
    "description": "",
    "dataFormat": "{0:#,##0.00}"
  },
  {
    "id": 476,
    "name": "FuelTankLevel",
    "displayName": "Fuel Tank Level",
    "description": "Percent of fuel left in tank",
    "dataFormat": "{0:#,##0.0}"
  },
  {
    "id": 433,
    "name": "fweaf",
    "displayName": "F-WEAF",
    "description": "Facility Weighted Equivalent Availability Factor =WEAF - ((EOCH/PH)*100) ",
    "dataFormat": "{0:#,##0.00}"
  },
  {
    "id": 501,
    "name": "GageHeight",
    "displayName": "Gage Height",
    "description": "GageHieght",
    "dataFormat": "{0:0,##0.00}"
  },
  {
    "id": 465,
    "name": "GainLossOverGen",
    "displayName": "Gain/Loss Over Generation",
    "description": "Addition Cost or Revenue from overgenerting in RT market",
    "dataFormat": "{0:#,##0.00}"
  },
  {
    "id": 712,
    "name": "GainLossTotalGen",
    "displayName": "Gain/Loss Total Generation",
    "description": "Addition Cost or Revenue from overgenerting or undergenerating in RT market",
    "dataFormat": "{0:#,##0.00}"
  },
  {
    "id": 466,
    "name": "GainLossUnderGen",
    "displayName": "Gain/Loss Under Generation",
    "description": "Addition Cost or Revenue from undergenerating in RT market",
    "dataFormat": "{0:#,##0.00}"
  },
  {
    "id": 487,
    "name": "GasHeatBTU",
    "displayName": "GasHeatBTU",
    "description": "Gas Heat Content in BTU",
    "dataFormat": "{0:#,##0.00}"
  },
  {
    "id": 485,
    "name": "GasTotalizer",
    "displayName": "Gas Totalizer",
    "description": "Gas Totalizer",
    "dataFormat": "{0:#,##0.00}"
  },
  {
    "id": 363,
    "name": "GHHAExpCapFcst",
    "displayName": "GHHAExpCapFcst",
    "description": "Garrad Hassan HAExpCapFcst",
    "dataFormat": "{0:0,##0.00}"
  },
  {
    "id": 364,
    "name": "GHHAPwrExp",
    "displayName": "GHHAPwrExp",
    "description": "Garrad Hassan HAPwrExp",
    "dataFormat": "{0:0,##0.00}"
  },
  {
    "id": 496,
    "name": "GHHAPwrFcst25",
    "displayName": "GHHAPwrFcst25",
    "description": "Garrad Hassan HAPwrFcst25",
    "dataFormat": "{0:0,##0.00}"
  },
  {
    "id": 497,
    "name": "GHHAPwrFcst50",
    "displayName": "GHHAPwrFcst50",
    "description": "Garrad Hassan HAPwrFcst50",
    "dataFormat": "{0:0,##0.00}"
  },
  {
    "id": 498,
    "name": "GHHAPwrFcst75",
    "displayName": "GHHAPwrFcst75",
    "description": "Garrad Hassan HAPwrFcst75",
    "dataFormat": "{0:0,##0.00}"
  },
  {
    "id": 365,
    "name": "GHHAWindSpeedFcst",
    "displayName": "GHHAWindSpeedFcst",
    "description": "Garrad Hassan HAWindSpeedFcst",
    "dataFormat": "{0:0,##0.00}"
  },
  {
    "id": 473,
    "name": "HAForecastMAPE",
    "displayName": "HA Forecast MAPE",
    "description": "Mean Average Percent Error between Hour Ahead forecast and actual generation (Act - HA Forecast)/Act",
    "dataFormat": "{0:#,##0.00}"
  },
  {
    "id": 518,
    "name": "Head",
    "displayName": "Head (ft)",
    "description": "Head (ft)",
    "dataFormat": "{0:0##,##0.00}"
  },
  {
    "id": 858,
    "name": "HeatEmissionRate",
    "displayName": "Heat Emission Rate",
    "description": "",
    "dataFormat": "{0:#,##0.0}"
  },
  {
    "id": 2011,
    "name": "Import Allocations",
    "displayName": "Import Allocations",
    "description": "Temp. Metric, Can be deleted after demo 4/4",
    "dataFormat": ""
  },
  {
    "id": 2010,
    "name": "Imports and Constraints",
    "displayName": "Imports and Constraints",
    "description": "Temp. Metric, Can be deleted after demo 4/4",
    "dataFormat": ""
  },
  {
    "id": 880,
    "name": "IncrementalEnergyCost",
    "displayName": "Incremental Energy Cost",
    "description": "",
    "dataFormat": "{0:#,##0.0}"
  },
  {
    "id": 480,
    "name": "InletGasTemperature",
    "displayName": "Inlet Gas Temperature",
    "description": "Gas Temperature at CT inlet",
    "dataFormat": "{0:##0.00}"
  },
  {
    "id": 479,
    "name": "InletPressure",
    "displayName": "Inlet Barometirc Pressure",
    "description": "Barometric Pressure at CT inlet",
    "dataFormat": "{0:##0.000}"
  },
  {
    "id": 478,
    "name": "InletRelH",
    "displayName": "Inlet Relative Humidity",
    "description": "Relative humity at CT inlet",
    "dataFormat": "{0:##0.00}"
  },
  {
    "id": 218,
    "name": "IntegratedDerateMW",
    "displayName": "Derate MWh",
    "description": "Integrated MW Reduction due to a derate or outage",
    "dataFormat": "{0:#,##0.0}"
  },
  {
    "id": 525,
    "name": "Interchange Component",
    "displayName": "ACE Interchange Component",
    "description": "The interchange component of the RAW ACE calculation",
    "dataFormat": "{0:##0.000}"
  },
  {
    "id": 632,
    "name": "InvertersAvailable",
    "displayName": "Inverters Available",
    "description": "Converts the variable direct current (DC) output of a photovoltaic (PV) solar panel into a utility f",
    "dataFormat": ""
  },
  {
    "id": 610,
    "name": "IRTH",
    "displayName": "Inactive Reserve Turbine-Hours (IRTH)",
    "description": "Manually entered Outage Mgmt Hours by Inactive Reserve Type",
    "dataFormat": "{0:##0.0}"
  },
  {
    "id": 865,
    "name": "ISOAvailMW",
    "displayName": "ISO Avail MW",
    "description": "",
    "dataFormat": "{0:#,##0.0}"
  },
  {
    "id": 872,
    "name": "ISOAvailMWApproved",
    "displayName": "ISO Avail MW Approved",
    "description": "Approved Availability from the ISO",
    "dataFormat": "{0:#,##0.0}"
  },
  {
    "id": 875,
    "name": "ISOStartUpCost",
    "displayName": "ISO Start Up Cost",
    "description": "",
    "dataFormat": "{0:#,##0.00}"
  },
  {
    "id": 460,
    "name": "kvolt",
    "displayName": "KV",
    "description": "",
    "dataFormat": "{0:#,##0.0}"
  },
  {
    "id": 637,
    "name": "KWhDelivered",
    "displayName": "Net KW",
    "description": "KW produced by plant, delivered to grid (Gross KW - Aux Power)",
    "dataFormat": "{0:#,##0}"
  },
  {
    "id": 477,
    "name": "Latest5MinTick",
    "displayName": "Latest 5 Min LMP Tick",
    "description": "Most recent 5 min LMP tick from Source",
    "dataFormat": "{0:##0.0}"
  },
  {
    "id": 412,
    "name": "LostProdPwr",
    "displayName": "Fault Lost Production",
    "description": "The amount energy lost, based on Expected Power, due to fault/alarm codes.  ",
    "dataFormat": "{0:#,##0.0}"
  },
  {
    "id": 2006,
    "name": "LSE Forecast",
    "displayName": "LSE Forecast",
    "description": "Temp. Metric, Can be deleted after demo 4/4",
    "dataFormat": ""
  },
  {
    "id": 407,
    "name": "ManAvailLostMin",
    "displayName": "Fault Lost Hours",
    "description": "The amount of time in hours due to fault/alarm codes.  ",
    "dataFormat": "{0:#,##0.0}"
  },
  {
    "id": 856,
    "name": "MaxDailyTransitions",
    "displayName": "Max Daily Transitions",
    "description": "",
    "dataFormat": "{0:#,##0.0}"
  },
  {
    "id": 776,
    "name": "MaxRampRate",
    "displayName": "Max Ramp Rate",
    "description": "",
    "dataFormat": "{0:#,##0.0}"
  },
  {
    "id": 777,
    "name": "MaxRunTime",
    "displayName": "Max Run Time",
    "description": "",
    "dataFormat": "{0:#,##0.0}"
  },
  {
    "id": 851,
    "name": "MaxTransitionCost",
    "displayName": "Max Transition Cost",
    "description": "",
    "dataFormat": "{0:#,##0.0}"
  },
  {
    "id": 356,
    "name": "MaxTurbAvail",
    "displayName": "Turbines Available",
    "description": "The number of turbines available to produce energy, if there is sufficient wind.",
    "dataFormat": "{0:#,##0}"
  },
  {
    "id": 611,
    "name": "MBTH",
    "displayName": "Mothballed Turbine-Hours (MBTH)",
    "description": "Manually entered Outage Mgmt Hours by Mothballed Type",
    "dataFormat": "{0:##0.0}"
  },
  {
    "id": 517,
    "name": "MDCMW",
    "displayName": "MDC (MW)",
    "description": "MDC (MW)",
    "dataFormat": "{0:0##,##0.00}"
  },
  {
    "id": 522,
    "name": "MetWindSpeed",
    "displayName": "Met Wind Speed",
    "description": "The wind speed of a met tower for a windfarm.",
    "dataFormat": "{0:##0.0}"
  },
  {
    "id": 778,
    "name": "MinOffTime",
    "displayName": "Min Off Time",
    "description": "",
    "dataFormat": "{0:#,##0.0}"
  },
  {
    "id": 779,
    "name": "MinRampRate",
    "displayName": "Min Ramp Rate",
    "description": "",
    "dataFormat": "{0:#,##0.0}"
  },
  {
    "id": 623,
    "name": "MinWindSpeed",
    "displayName": "Min Wind Speed",
    "description": "The lowest wind speed recorded during the given time period",
    "dataFormat": "{0:#,##0.0}"
  },
  {
    "id": 48,
    "name": "moh",
    "displayName": "MOH",
    "description": "Number of Hours where Maintenance outage exists (accounts for partial hours)",
    "dataFormat": "{0:#,##0.0}"
  },
  {
    "id": 2000,
    "name": "Monthly MW",
    "displayName": "Monthly MW",
    "description": "Temp. Metric, Can be deleted after demo 4/4",
    "dataFormat": ""
  },
  {
    "id": 2001,
    "name": "Monthly Update",
    "displayName": "Monthly Update",
    "description": "Temp. Metric, Can be deleted after demo 4/4",
    "dataFormat": ""
  },
  {
    "id": 877,
    "name": "MonthlyGrossMarginBudget",
    "displayName": "Monthly Gross Margin Budget",
    "description": "",
    "dataFormat": "{0:#,##0.00}"
  },
  {
    "id": 604,
    "name": "MTH",
    "displayName": "Maintenance Turbine-Hours (MTH)",
    "description": "Total number of hours that turbines are in a Maintenance Outage State",
    "dataFormat": "{0:##0.0}"
  },
  {
    "id": 780,
    "name": "MustOfferQualified",
    "displayName": "Must Offer Qualified",
    "description": "",
    "dataFormat": "{0:#,##0.0}"
  },
  {
    "id": 470,
    "name": "MVAR",
    "displayName": "MVAR",
    "description": "",
    "dataFormat": "{0:#,##0.0}"
  },
  {
    "id": 1,
    "name": "mwhDelivered",
    "displayName": "Net MW",
    "description": "MW produced by plant, delivered to grid (Gross MW - Aux Power)",
    "dataFormat": "{0:#,##0.0}"
  },
  {
    "id": 11,
    "name": "mwhScheduled",
    "displayName": "Scheduled MW",
    "description": "Energy Schedule (MWh)",
    "dataFormat": "{0:#,##0.0}"
  },
  {
    "id": 51,
    "name": "mwhSettled",
    "displayName": "Settled MW",
    "description": "Number of MW produced, and settled with the ISO or counterparty.",
    "dataFormat": "{0:#,##0.0}"
  },
  {
    "id": 624,
    "name": "MxWindSpeed",
    "displayName": "Max Wind Speed",
    "description": "The highest wind speed recorded during the given time period",
    "dataFormat": "{0:#,##0.0}"
  },
  {
    "id": 116,
    "name": "NacelleWindSpeed",
    "displayName": "Turbine Wind Speed",
    "description": "Average Wind Speed from turbines or met towers",
    "dataFormat": "{0:#,##0.0}"
  },
  {
    "id": 115,
    "name": "NacellPositionDegreesN",
    "displayName": "Nacelle Position (Degrees)",
    "description": "The average/integrated position in degrees of the turbines Nacelle",
    "dataFormat": "{0:#,##0.0}"
  },
  {
    "id": 530,
    "name": "NetMwAccumated",
    "displayName": "Net MW (Accumulator)",
    "description": "NET MW for a given location, based on an accumulated value from SCADA/Data Historian",
    "dataFormat": "{0:#,##0.0}"
  },
  {
    "id": 876,
    "name": "NoLoadOrMinGenCost",
    "displayName": "No Load or Min Gen Cost",
    "description": "",
    "dataFormat": "{0:#,##0.00}"
  },
  {
    "id": 781,
    "name": "NonSpinReserveCapacity",
    "displayName": "Non Spin Reserve Capacity",
    "description": "",
    "dataFormat": "{0:#,##0.0}"
  },
  {
    "id": 853,
    "name": "NotificationTime",
    "displayName": "Notification Time",
    "description": "",
    "dataFormat": "{0:#,##0.0}"
  },
  {
    "id": 448,
    "name": "NumFaults",
    "displayName": "# Faults",
    "description": "The total count of all faults for each turbine for the selected time period.",
    "dataFormat": "{0:#,##0}"
  },
  {
    "id": 444,
    "name": "NumTurbines",
    "displayName": "Number Of Turbines",
    "description": "The total number of turbines located at the site, derived from Location Attributes",
    "dataFormat": "{0:#,##0}"
  },
  {
    "id": 883,
    "name": "OfferCurveEnergyCost",
    "displayName": "Offer Curve Energy Cost",
    "description": "",
    "dataFormat": "{0:#,##0.0}"
  },
  {
    "id": 606,
    "name": "oFTH",
    "displayName": "OMC Forced Turbine-Hours (oFTH)",
    "description": "Total number of hours that turbines are in an OMC Forced Outage State",
    "dataFormat": "{0:##0.0}"
  },
  {
    "id": 607,
    "name": "oMTH",
    "displayName": "OMC Maintenance Turbine-Hours (oMTH)",
    "description": "Total number of hours that turbines are in an OMC Maintenance Outage State",
    "dataFormat": "{0:##0.0}"
  },
  {
    "id": 431,
    "name": "operatingEfficiency",
    "displayName": "Operating Efficiency",
    "description": "Percent of Power Curve (Net MW/Expected Power * 100%)",
    "dataFormat": "{0:#,##0.00}"
  },
  {
    "id": 188,
    "name": "operatingMargin",
    "displayName": "Actual Margin",
    "description": "Actual Revenue from the plant.  = Exepcted Margin + Startup Margin + Gain/Loss Over Generation + Gai",
    "dataFormat": "{0:#,##0}"
  },
  {
    "id": 531,
    "name": "OperatingReserves",
    "displayName": "Operating Reserves",
    "description": "Actual Operating Reserves deployed",
    "dataFormat": "{0:#,##0.0}"
  },
  {
    "id": 532,
    "name": "OperatingReservesRequired",
    "displayName": "Operating Reserves Required",
    "description": "Amount of Operating Reserves that are required based on scheduled MW",
    "dataFormat": "{0:#,##0.0}"
  },
  {
    "id": 782,
    "name": "OpReserveMaxRampRate",
    "displayName": "Op Reserve Max Ramp Rate",
    "description": "",
    "dataFormat": "{0:#,##0.0}"
  },
  {
    "id": 783,
    "name": "OpReserveMinRampRate",
    "displayName": "Op Reserve Min Ramp Rate",
    "description": "",
    "dataFormat": "{0:#,##0.0}"
  },
  {
    "id": 608,
    "name": "oPTH",
    "displayName": "OMC Planned Turbine-Hours (oPTH)",
    "description": "Total number of hours that turbines are in an OMC Planned Outage State",
    "dataFormat": "{0:##0.0}"
  },
  {
    "id": 500,
    "name": "OutflowForecast",
    "displayName": "OutflowForecast",
    "description": "Outflow forecast - Regulated",
    "dataFormat": "{0:0,##0.00}"
  },
  {
    "id": 430,
    "name": "outputFactor",
    "displayName": "Output Factor",
    "description": "Percent of actual plant loading when on-line",
    "dataFormat": "{0:#,##0.00}"
  },
  {
    "id": 291,
    "name": "OwnerShareAvailability",
    "displayName": "OwnerShareAvailability",
    "description": null,
    "dataFormat": "{0:#,##0.0}"
  },
  {
    "id": 292,
    "name": "OwnerShareAvailabilityAdjDerate",
    "displayName": "OwnerShareAvailabilityAdjDerate",
    "description": null,
    "dataFormat": "{0:#,##0.0}"
  },
  {
    "id": 295,
    "name": "OwnerShareCapability",
    "displayName": "OwnerShareCapability",
    "description": null,
    "dataFormat": "{0:#,##0.0}"
  },
  {
    "id": 294,
    "name": "OwnerShareCapabilityAdjDerate",
    "displayName": "OwnerShareCapabilityAdjDerate",
    "description": null,
    "dataFormat": "{0:#,##0.0}"
  },
  {
    "id": 290,
    "name": "OwnerShareDerate",
    "displayName": "OwnerShareDerate",
    "description": null,
    "dataFormat": "{0:#,##0.0}"
  },
  {
    "id": 260,
    "name": "OwnerShareMwhDelivered",
    "displayName": "OwnerShareDeliveredMWh",
    "description": null,
    "dataFormat": "{0:#,##0.0}"
  },
  {
    "id": 261,
    "name": "OwnerShareSetpointMW",
    "displayName": "OwnerShareSetpointMW",
    "description": null,
    "dataFormat": "{0:#,##0.0}"
  },
  {
    "id": 601,
    "name": "PDTH",
    "displayName": "Period Turbine-Hours (PDTH)",
    "description": "Total number of turbine hours (number of hours * number of turbines)",
    "dataFormat": "{0:##0.0}"
  },
  {
    "id": 439,
    "name": "PH",
    "displayName": "Period Hrs",
    "description": "Total number of hours in given period",
    "dataFormat": "{0:#,##0}"
  },
  {
    "id": 474,
    "name": "PipePressure",
    "displayName": "Pipe Pressure",
    "description": "",
    "dataFormat": "{0:##0.0}"
  },
  {
    "id": 475,
    "name": "PipeTemp",
    "displayName": "Pipe Temperature",
    "description": "",
    "dataFormat": "{0:#,##0.0}"
  },
  {
    "id": 885,
    "name": "PJM RTONSR",
    "displayName": "RTO Non-Synch Res",
    "description": "",
    "dataFormat": "{0:#,##0.0}"
  },
  {
    "id": 94,
    "name": "PJM RTORC",
    "displayName": "RTO Regulation Capability",
    "description": "",
    "dataFormat": "{0:#,##0.0}"
  },
  {
    "id": 93,
    "name": "PJM RTORP",
    "displayName": "RTO Regulation Performance",
    "description": "",
    "dataFormat": "{0:#,##0.0}"
  },
  {
    "id": 884,
    "name": "PJM RTOSR",
    "displayName": "RTO Synch Res",
    "description": "",
    "dataFormat": "{0:#,##0.0}"
  },
  {
    "id": 890,
    "name": "PJMDasrMCP",
    "displayName": "PJM DASR MCP",
    "description": "",
    "dataFormat": "{0:#,##0.0}"
  },
  {
    "id": 887,
    "name": "PJMNonSynchVolume",
    "displayName": "PJM Non Synch Volume",
    "description": "",
    "dataFormat": "{0:#,##0.0}"
  },
  {
    "id": 888,
    "name": "PJMRegAMileageRatio",
    "displayName": "PJM RegA Mileage Ratio",
    "description": "",
    "dataFormat": "{0:#,##0.0}"
  },
  {
    "id": 889,
    "name": "PJMRegDMileageRatio",
    "displayName": "PJM RegD Mileage Ratio",
    "description": "",
    "dataFormat": "{0:#,##0.0}"
  },
  {
    "id": 62,
    "name": "poh",
    "displayName": "POH",
    "description": "Number of Hours where planned outage exists (accounts for partial hours)",
    "dataFormat": "{0:#,##0.0}"
  },
  {
    "id": 504,
    "name": "PrecipitationNOAA",
    "displayName": "NOAA Precipitation",
    "description": "Precipitation(NOAA)",
    "dataFormat": "{0:0,##0.00}"
  },
  {
    "id": 621,
    "name": "ProductionEfficiency",
    "displayName": "Production Efficiency",
    "description": "Percent of Power Curve (Net MW/Expected Power * 100%).  This is a measure of how well the unit is pe",
    "dataFormat": "{0:#,##0.00}"
  },
  {
    "id": 630,
    "name": "ProfitandLoss",
    "displayName": "Profit/Loss",
    "description": "Profit and Loss for a given unit, calculated by revenue minus production costs",
    "dataFormat": "{0:#,##0.00}"
  },
  {
    "id": 528,
    "name": "PseudoTieEnabled",
    "displayName": "Pseudo Tie Enabled Status",
    "description": "Status indicator describing if a Pseudo Tie is enabled (on/off)",
    "dataFormat": ""
  },
  {
    "id": 529,
    "name": "PseudoTieRequested",
    "displayName": "Pseudo Tie Requested",
    "description": "Requested MW on a Pseudo Tie from the sync",
    "dataFormat": "{0:#,##0.0}"
  },
  {
    "id": 605,
    "name": "PTH",
    "displayName": "Planned Turbine-Hours (PTH)",
    "description": "Total number of hours that turbines are in a Planned Outage State",
    "dataFormat": "{0:##0.0}"
  },
  {
    "id": 878,
    "name": "PumpingHours",
    "displayName": "Pumping Hours",
    "description": "",
    "dataFormat": "{0:#,##0.0}"
  },
  {
    "id": 2013,
    "name": "RA Commitments",
    "displayName": "RA Commitments",
    "description": "Temp. Metric, Can be deleted after demo 4/4",
    "dataFormat": ""
  },
  {
    "id": 2003,
    "name": "RAForecast",
    "displayName": "RAForecast",
    "description": "Temp. Metric, Can be deleted after demo 4/4",
    "dataFormat": ""
  },
  {
    "id": 539,
    "name": "RampRate",
    "displayName": "Ramp Rate",
    "description": "The rate of change (MW/Minute) in output from a power plant.  Usually a manufacturer's specification",
    "dataFormat": "{0:##0.0}"
  },
  {
    "id": 535,
    "name": "RampRate10Min",
    "displayName": "Ramp Rate (10 Min)",
    "description": "10 Minute Ramp Rate",
    "dataFormat": "{0:##0.0}"
  },
  {
    "id": 451,
    "name": "RegAvailMW",
    "displayName": "Reg Available MW",
    "description": "Regulation is an ancillary service where plant can quickly move/change generation output based on a ",
    "dataFormat": "{0:#,##0.0}"
  },
  {
    "id": 452,
    "name": "RegAwardedMW",
    "displayName": "Reg Awarded MW",
    "description": "The Amount of reugalation awarded to the plant by the market.  ",
    "dataFormat": "{0:#,##0.0}"
  },
  {
    "id": 784,
    "name": "Registered",
    "displayName": "Registered",
    "description": "",
    "dataFormat": "{0:#,##0.0}"
  },
  {
    "id": 85,
    "name": "RegMaxMW",
    "displayName": "Reg Max",
    "description": "The maximum amount of energy that a plant must be producing in order to provide Regulation Services",
    "dataFormat": "{0:#,##0.0}"
  },
  {
    "id": 785,
    "name": "RegMaxRampRate",
    "displayName": "Reg Max Ramp Rate",
    "description": "",
    "dataFormat": "{0:#,##0.0}"
  },
  {
    "id": 84,
    "name": "RegMinMW",
    "displayName": "Reg Min MW",
    "description": "The minimum amount of energy that a plant must be producing in order to provide Regulation Services",
    "dataFormat": "{0:#,##0.0}"
  },
  {
    "id": 786,
    "name": "RegMinRampRate",
    "displayName": "Reg Min Ramp Rate",
    "description": "",
    "dataFormat": "{0:#,##0.0}"
  },
  {
    "id": 873,
    "name": "RegPrice",
    "displayName": "Regulation Price",
    "description": "",
    "dataFormat": "{0:#,##0.00}"
  },
  {
    "id": 20,
    "name": "RelativeHumidity",
    "displayName": "Relative Humidity",
    "description": "RH measured at unit",
    "dataFormat": "{0:#,##0.0}"
  },
  {
    "id": 874,
    "name": "ReservePrice",
    "displayName": "Reserve Price",
    "description": "",
    "dataFormat": "{0:#,##0.00}"
  },
  {
    "id": 63,
    "name": "reserveShutdownHours",
    "displayName": "RSH",
    "description": "Reserve Shutdown hours for these units are computed by subtracting the reported service hours and al",
    "dataFormat": "{0:#,##0}"
  },
  {
    "id": 509,
    "name": "ReservoirElevation",
    "displayName": "ReservoirElevation (ft)",
    "description": "ReservoirElevation (ft)",
    "dataFormat": "{0:0##,##0.00}"
  },
  {
    "id": 511,
    "name": "ReservoirStorage",
    "displayName": "ReservoirStorage (dsf)",
    "description": "ReservoirStorage (dsf)",
    "dataFormat": "{0:0##,##0.00}"
  },
  {
    "id": 787,
    "name": "ResourceAdequacyCapacity",
    "displayName": "Resource Adequacy Capacity",
    "description": "",
    "dataFormat": "{0:#,##0.0}"
  },
  {
    "id": 788,
    "name": "ResourceAdequacyFlag",
    "displayName": "Resource Adequacy Flag",
    "description": "",
    "dataFormat": "{0:#,##0.0}"
  },
  {
    "id": 643,
    "name": "RevenueGenerationAccumulated",
    "displayName": "Actual Generation To Date",
    "description": "The amount of generation accumlated through a time period based on accumlator from Scada/PI",
    "dataFormat": "{0:#,##0.0}"
  },
  {
    "id": 495,
    "name": "RiverFlowActualCFS",
    "displayName": "RiverFlowActualCFS",
    "description": "River Flow Actual in CFS",
    "dataFormat": "{0:0,##0.00}"
  },
  {
    "id": 493,
    "name": "RiverFlowForecastCFS",
    "displayName": "RiverFlowForecastCFS",
    "description": "RiverFlow forecast in CFS",
    "dataFormat": "{0:0,##0.00}"
  },
  {
    "id": 513,
    "name": "RiverRampRate",
    "displayName": "RiverRampRate",
    "description": "River Ramp Rate",
    "dataFormat": "{0:0##,##0.00}"
  },
  {
    "id": 2009,
    "name": "RMR",
    "displayName": "RMR",
    "description": "Temp. Metric, Can be deleted after demo 4/4",
    "dataFormat": ""
  },
  {
    "id": 2017,
    "name": "RT Revenue",
    "displayName": "RT Revenue",
    "description": "RT Revenue",
    "dataFormat": "{0:#,##0.00}"
  },
  {
    "id": 102,
    "name": "RT Spot energy price",
    "displayName": "RT Price",
    "description": "",
    "dataFormat": "{0:#,##0.00}"
  },
  {
    "id": 612,
    "name": "RTH",
    "displayName": "Retired Unit Turbine-Hours (RTH)",
    "description": "Manually entered Outage Mgmt Hours Retired Type",
    "dataFormat": "{0:##0.0}"
  },
  {
    "id": 711,
    "name": "RTPrediction",
    "displayName": "RT Prediction",
    "description": "TBD",
    "dataFormat": ""
  },
  {
    "id": 609,
    "name": "RUTH",
    "displayName": "Resource Unavailable Turbine-Hours (RUTH)",
    "description": "Total number of hours turbines are in any unavailable state (PDTH-CTH-RSTH-FTH-MTH-PTH-IRTH-MBTH-RTH",
    "dataFormat": "{0:##0.0}"
  },
  {
    "id": 5,
    "name": "SetPointMw",
    "displayName": "Set Point MW",
    "description": "Requested MW from generating unit",
    "dataFormat": "{0:#,##0.0}"
  },
  {
    "id": 505,
    "name": "SnowLevel",
    "displayName": "Freezing Level",
    "description": "SnowLevel",
    "dataFormat": "{0:0,##0.00}"
  },
  {
    "id": 2015,
    "name": "Solar TAC",
    "displayName": "Solar TAC",
    "description": "Temp. Metric, Can be deleted after demo 4/4",
    "dataFormat": ""
  },
  {
    "id": 636,
    "name": "SolarCellTempActual",
    "displayName": "Solar Cell Temp Actual",
    "description": "Ambient temperature measured on a given solar cell or a range of solar cells.  Typically reported as",
    "dataFormat": "{0:#,##0.0}"
  },
  {
    "id": 863,
    "name": "SolarCellTempForecast",
    "displayName": "Solar Cell Temp Forecast",
    "description": "",
    "dataFormat": ""
  },
  {
    "id": 631,
    "name": "SolarIrradianceActual",
    "displayName": "Solar Irradiance Actual",
    "description": "The density of radiation incident on a given surface usually expressed in watts per square meter. W?",
    "dataFormat": ""
  },
  {
    "id": 862,
    "name": "SolarIrradianceForecast",
    "displayName": "Solar Irradiance Forecast",
    "description": "",
    "dataFormat": ""
  },
  {
    "id": 514,
    "name": "Spill",
    "displayName": "Spill (cfs)",
    "description": "Spill (cfs)",
    "dataFormat": "{0:#,##0.0}"
  },
  {
    "id": 453,
    "name": "SpinAvailMW",
    "displayName": "Spin Available MW",
    "description": "Spinning Reserve is an ancillary service where plant can move/change generation in short timeframe o",
    "dataFormat": "{0:#,##0.0}"
  },
  {
    "id": 454,
    "name": "SpinAwardedMW",
    "displayName": "Spin Awarded MW",
    "description": "Spinning Reserve is an ancillary service where plant can move/change generation in short timeframe o",
    "dataFormat": "{0:#,##0.0}"
  },
  {
    "id": 533,
    "name": "Spinning ReservesRequired",
    "displayName": "Spinning Reserves Required",
    "description": "Amount of Spinning Reserves that are required based on scheduled MW",
    "dataFormat": "{0:#,##0.0}"
  },
  {
    "id": 789,
    "name": "SpinReserveCapacity",
    "displayName": "Spin Reserve Capacity",
    "description": "",
    "dataFormat": "{0:#,##0.0}"
  },
  {
    "id": 859,
    "name": "Start-UpAux",
    "displayName": "Start-Up Aux",
    "description": "",
    "dataFormat": "{0:#,##0.0}"
  },
  {
    "id": 491,
    "name": "StartHour",
    "displayName": "UnitStartHour",
    "description": "Unit or Plant Start Hour",
    "dataFormat": "{0:0,##0}"
  },
  {
    "id": 464,
    "name": "StartMargin",
    "displayName": "Start Margin",
    "description": "",
    "dataFormat": "{0:#,##0.00}"
  },
  {
    "id": 791,
    "name": "StartupCost",
    "displayName": "Startup Cost",
    "description": "",
    "dataFormat": "{0:#,##0.0}"
  },
  {
    "id": 461,
    "name": "StartupHR",
    "displayName": "Startup Heat Rate",
    "description": "Heat Rate during Startup period as additional fuel is consumed to start the unit",
    "dataFormat": "{0:#,##0.0}"
  },
  {
    "id": 792,
    "name": "StartupTime",
    "displayName": "Startup Time",
    "description": "",
    "dataFormat": "{0:#,##0.0}"
  },
  {
    "id": 494,
    "name": "StreamFlowActualCFS",
    "displayName": "StreamFlowActualCFS",
    "description": "Stream Flow Actual in CFS",
    "dataFormat": "{0:0,##0.00}"
  },
  {
    "id": 492,
    "name": "StreamFlowForecastCFS",
    "displayName": "StreamFlowForecastCFS",
    "description": "StreamFlow forecast in CFS",
    "dataFormat": "{0:0,##0.00}"
  },
  {
    "id": 879,
    "name": "SynchronousHours",
    "displayName": "Synchronous Hours",
    "description": "",
    "dataFormat": "{0:#,##0.0}"
  },
  {
    "id": 516,
    "name": "TailwaterElevation",
    "displayName": "TailwaterElevation (cfs)",
    "description": "TailwaterElevation (cfs)",
    "dataFormat": "{0:0##,##0.00}"
  },
  {
    "id": 10,
    "name": "Temperature Actual",
    "displayName": "Temperature",
    "description": "Temperature measured at unit",
    "dataFormat": "{0:#,##0.0}"
  },
  {
    "id": 12,
    "name": "Temperature Forecast",
    "displayName": "Forecasted Temp",
    "description": "",
    "dataFormat": "{0:#,##0.0}"
  },
  {
    "id": 640,
    "name": "TheoreticalProductionHours",
    "displayName": "Theoretical Production Hours",
    "description": "The hours in the Period when minimum POA irradiance conditions persisting for periods greater than o",
    "dataFormat": "{0:#,##0.0}"
  },
  {
    "id": 2018,
    "name": "Total Revenue",
    "displayName": "Total Revenue",
    "description": "Total Revenue",
    "dataFormat": "{0:#,##0.00}"
  },
  {
    "id": 205,
    "name": "TotalCapability",
    "displayName": "Capability/NDC",
    "description": "Amount of energy a unit can produce, adjusted for weather conditions, and power curve",
    "dataFormat": "{0:#,##0.0}"
  },
  {
    "id": 92,
    "name": "totalFossilMW",
    "displayName": "Total Fossil MW",
    "description": null,
    "dataFormat": "{0:#,##0.00}"
  },
  {
    "id": 620,
    "name": "TotalTurbinesCommError",
    "displayName": "Total Turbines Having Communications Error",
    "description": "The total number of turbines having communications issues",
    "dataFormat": "{0:##0}"
  },
  {
    "id": 644,
    "name": "TotalTurbinesInOutage",
    "displayName": "Total Turbines In Outage",
    "description": "The total number of turbines in a an outage.",
    "dataFormat": "{0:#,##0}"
  },
  {
    "id": 91,
    "name": "totalWindMW",
    "displayName": "Total Wind MW",
    "description": null,
    "dataFormat": "{0:#,##0.00}"
  },
  {
    "id": 614,
    "name": "TotTurbinesAutoStop",
    "displayName": "Total Turbines Automatically Stopped",
    "description": "The number of turbines that have been automatically stopped by the SCADA system",
    "dataFormat": "{0:##0}"
  },
  {
    "id": 618,
    "name": "TotTurbinesAvailOfflineState",
    "displayName": "Total Turbines Available Offline State",
    "description": "The total number of turbines that are available, but are in an offline state",
    "dataFormat": "{0:##0}"
  },
  {
    "id": 617,
    "name": "TotTurbinesHighWindState",
    "displayName": "Total Turbines In High Wind State",
    "description": "The total number of turbines stopped due to High Wind conditions",
    "dataFormat": "{0:##0}"
  },
  {
    "id": 616,
    "name": "TotTurbinesLowWindState",
    "displayName": "Total Turbines In Low Wind State",
    "description": "The total number of turbines stopped due to Low Wind conditions",
    "dataFormat": "{0:##0}"
  },
  {
    "id": 613,
    "name": "TotTurbinesManualStop",
    "displayName": "Total Turbines In Manual Stop",
    "description": "The number of turbines that have been manually stopped according to fault events",
    "dataFormat": "{0:##0}"
  },
  {
    "id": 619,
    "name": "TotTurbinesMiscOutageState",
    "displayName": "Total Turbines in Misc Outage State",
    "description": "The total number of turbines in a miscelleanous outage state",
    "dataFormat": "{0:##0}"
  },
  {
    "id": 615,
    "name": "TotTurbinesOutOfService",
    "displayName": "Total Turbines Out Of Service",
    "description": "The total number of turbines in an Out Of Service state",
    "dataFormat": "{0:##0}"
  },
  {
    "id": 850,
    "name": "TransitionCost",
    "displayName": "Transition Cost",
    "description": "",
    "dataFormat": "{0:#,##0.0}"
  },
  {
    "id": 855,
    "name": "TransitionEnergy",
    "displayName": "Transition Energy",
    "description": "",
    "dataFormat": "{0:#,##0.0}"
  },
  {
    "id": 854,
    "name": "TransitionFuel",
    "displayName": "Transition Fuel",
    "description": "",
    "dataFormat": "{0:#,##0.0}"
  },
  {
    "id": 852,
    "name": "TransitionRampTime",
    "displayName": "Transition Ramp Time",
    "description": "",
    "dataFormat": "{0:#,##0.0}"
  },
  {
    "id": 527,
    "name": "Transmission Available",
    "displayName": "Transmission Available",
    "description": "The amount of transmission that is available, that limits the flow on a given Pseudo-Tie",
    "dataFormat": "{0:#,##0.0}"
  },
  {
    "id": 67,
    "name": "tripCount",
    "displayName": "Trips",
    "description": "Number of Unit or Plant Trip Events",
    "dataFormat": "{0:#,##0}"
  },
  {
    "id": 2002,
    "name": "True up",
    "displayName": "True up",
    "description": "Temp. Metric, Can be deleted after demo 4/4",
    "dataFormat": ""
  },
  {
    "id": 521,
    "name": "TurbineCapacityChange",
    "displayName": "Turbine Capacity Change",
    "description": "The difference betwen expected turbines - available turbines.",
    "dataFormat": "{0:##0.0}"
  },
  {
    "id": 629,
    "name": "TurbineFaultCode",
    "displayName": "Turbine Fault Code",
    "description": "Actual Fault Code from the turbine",
    "dataFormat": ""
  },
  {
    "id": 515,
    "name": "TurbineFlow",
    "displayName": "TurbineFlow (cfs)",
    "description": "TurbineFlow (cfs)",
    "dataFormat": "{0:0##,##0.00}"
  },
  {
    "id": 627,
    "name": "TurbineHighWindStateFlag",
    "displayName": "Turbine High Wind State Flag",
    "description": "Indicator if the trurbine is in a high wind state",
    "dataFormat": ""
  },
  {
    "id": 626,
    "name": "TurbineLowWindStateFlag",
    "displayName": "Turbine Low Wind State Flag",
    "description": "Indicator if the trurbine is in a low wind state",
    "dataFormat": ""
  },
  {
    "id": 483,
    "name": "TurbineRPM",
    "displayName": "Turbine RPM",
    "description": "Turbine RPM",
    "dataFormat": "{0:#,##0.00}"
  },
  {
    "id": 445,
    "name": "TurbinesExpected",
    "displayName": "Turbines Expected",
    "description": "The number of turbines expected to be available for generation, based on input/forecast from Unit Ca",
    "dataFormat": "{0:#,##0}"
  },
  {
    "id": 447,
    "name": "TurbinesFaulted",
    "displayName": "Turbines Faulted",
    "description": "Turbines not operating due to fault condition",
    "dataFormat": "{0:#,##0}"
  },
  {
    "id": 523,
    "name": "TurbineSize",
    "displayName": "Turbine Size",
    "description": "The Boilerplate capacity of a single turbine at a windfarm..",
    "dataFormat": "{0:##0.0}"
  },
  {
    "id": 635,
    "name": "TurbineStartupState",
    "displayName": "Turbine Startup State",
    "description": "A state flag indicating a turbine is syncing",
    "dataFormat": "{0:#,##0.00}"
  },
  {
    "id": 446,
    "name": "TurbinesUnavailable",
    "displayName": "Turbines Unavailable",
    "description": "The number of turbines not on line and producting electricity",
    "dataFormat": "{0:#,##0}"
  },
  {
    "id": 481,
    "name": "TurningGear",
    "displayName": "Turning Gear",
    "description": "Turning Gear engaged",
    "dataFormat": "{0:0}"
  },
  {
    "id": 536,
    "name": "UnitAvailable",
    "displayName": "Unit Available",
    "description": "Is the Unit Available",
    "dataFormat": "{0:#}"
  },
  {
    "id": 881,
    "name": "UnitRunEnded",
    "displayName": "Unit Run Ended",
    "description": "",
    "dataFormat": "{0:#,##0.0}"
  },
  {
    "id": 490,
    "name": "UnitsOnAGC",
    "displayName": "Units On AGC",
    "description": "Number of units on AGC",
    "dataFormat": "{0:##0.00}"
  },
  {
    "id": 793,
    "name": "VarOAndM",
    "displayName": "Var O And M",
    "description": "",
    "dataFormat": "{0:#,##0.0}"
  },
  {
    "id": 441,
    "name": "WEFOF",
    "displayName": "W-EFOF",
    "description": "Weighted Equivalent Forced Outage Factor = (S((FOH+EFDH)* NOC) / S (PH*NOC) ) * 100 Event Types: FOH",
    "dataFormat": "{0:#,##0.0}"
  },
  {
    "id": 440,
    "name": "WEFOR",
    "displayName": "W-EFOR",
    "description": "Weighted Equivalent Forced Outage Rate = (S((FOH+EFDH)*NOC)/S((FOH+SH+EFDHRS)*NOC))*100% Event Types",
    "dataFormat": "{0:#,##0.0}"
  },
  {
    "id": 660,
    "name": "weightedCommAvail",
    "displayName": "Weighted Commercial Availability",
    "description": "The weighted value of the Turbine?s Commercial Availability per Turbine NPC.",
    "dataFormat": "{0:0,##0.00}"
  },
  {
    "id": 661,
    "name": "weightedTotInRangeMin",
    "displayName": "Weighted Total In Range Minutes",
    "description": "The weighted value of the Turbine?s Commercial Availability for when the Turbine is In Wind Range.",
    "dataFormat": "{0:0,##0.00}"
  },
  {
    "id": 482,
    "name": "WetBulbTemperature",
    "displayName": "Wet Bulb Temperature",
    "description": "Wet Bulb Temperature",
    "dataFormat": "{0:#,##0.00}"
  },
  {
    "id": 2014,
    "name": "Wind TAC",
    "displayName": "Wind TAC",
    "description": "Temp. Metric, Can be deleted after demo 4/4",
    "dataFormat": ""
  },
  {
    "id": 625,
    "name": "WindState",
    "displayName": "Wind State",
    "description": "Wind State describes the wind speed in respect to the turbine cut in and cut out characteristics",
    "dataFormat": ""
  },
  {
    "id": 437,
    "name": "wppa",
    "displayName": "WPPA",
    "description": "Weighted Percentage of Planned Availability = (Sum of each unit's (Unit NOC*( PH-SOH-FOH-EPDH-EUDH))",
    "dataFormat": "{0:#,##0.00}"
  }
]